redishermes/__init__.py
redishermes/hermes.py
redishermes-0.1.0.dist-info/DESCRIPTION.rst
redishermes-0.1.0.dist-info/METADATA
redishermes-0.1.0.dist-info/RECORD
redishermes-0.1.0.dist-info/WHEEL
redishermes-0.1.0.dist-info/metadata.json
redishermes-0.1.0.dist-info/top_level.txt
