Metadata-Version: 2.0
Name: redishermes
Version: 0.1.0
Summary: A simple redis backed message queue
Home-page: https://github.com/cristiandima/redishermes
Author: Cristian Dima
Author-email: UNKNOWN
License: MIT
Keywords: redis task message queue broker
Platform: UNKNOWN
Classifier: Development Status :: 5 - Production/Stable
Classifier: Intended Audience :: Developers
Classifier: License :: OSI Approved :: MIT License
Classifier: Programming Language :: Python :: 3.5
